LICENSE
README.md
setup.cfg
setup.py
VizPack/__init__.py
VizPack/vizpack.py
VizPack.egg-info/PKG-INFO
VizPack.egg-info/SOURCES.txt
VizPack.egg-info/dependency_links.txt
VizPack.egg-info/not-zip-safe
VizPack.egg-info/requires.txt
VizPack.egg-info/top_level.txt