Metadata-Version: 2.1
Name: VizPack
Version: 1.0.2
Summary: Tool for plotting visualizations from Pandas DataFrame
Home-page: https://github.com/invest41/VizPack
Author: Alao David I.
Author-email: alaodavid41@gmail.com
License: MIT
Platform: UNKNOWN
License-File: LICENSE
